relax/__init__.py
relax/_modidx.py
relax/base.py
relax/data_module.py
relax/docs.py
relax/evaluate.py
relax/explain.py
relax/import_essentials.py
relax/ml_model.py
relax/strategy.py
relax/utils.py
relax/data_utils/__init__.py
relax/data_utils/features.py
relax/data_utils/preprocessing.py
relax/data_utils/transforms.py
relax/legacy/__init__.py
relax/legacy/ckpt_manager.py
relax/legacy/import_essentials.py
relax/legacy/logger.py
relax/legacy/module.py
relax/legacy/trainer.py
relax/legacy/utils.py
relax/methods/__init__.py
relax/methods/base.py
relax/methods/cchvae.py
relax/methods/clue.py
relax/methods/counternet.py
relax/methods/dice.py
relax/methods/l2c.py
relax/methods/proto.py
relax/methods/sphere.py
relax/methods/vaecf.py
relax/methods/vanilla.py
jax_relax-0.2.8.dist-info/LICENSE
jax_relax-0.2.8.dist-info/METADATA
jax_relax-0.2.8.dist-info/WHEEL
jax_relax-0.2.8.dist-info/entry_points.txt
jax_relax-0.2.8.dist-info/top_level.txt
jax_relax-0.2.8.dist-info/RECORD
