Metadata-Version: 2.1
Name: jax-relax
Version: 0.2.8
Summary: JAX-based Recourse Explanation Library
Home-page: https://github.com/birkhoffg/jax-relax
Author: BirkhoffG
Author-email: 26811230+BirkhoffG@users.noreply.github.com
License: Apache Software License 2.0
Keywords: JAX,Recourse,Explanation,Interpretability,Machine Learning
Classifier: Development Status :: 4 - Beta
Classifier: Intended Audience :: Developers
Classifier: Natural Language :: English
Classifier: Programming Language :: Python :: 3.9
Classifier: Programming Language :: Python :: 3.10
Classifier: Programming Language :: Python :: 3.11
Classifier: Programming Language :: Python :: 3.12
Classifier: License :: OSI Approved :: Apache Software License
Requires-Python: >=3.9
License-File: LICENSE
Requires-Dist: scikit-learn >=1.0.2
Requires-Dist: pandas
Requires-Dist: jax[cpu]
Requires-Dist: tqdm
Requires-Dist: optax
Requires-Dist: pydantic <2,>=1.9.0
Requires-Dist: jax-tqdm
Requires-Dist: einops
Requires-Dist: keras <3.4.0,>=3.0.3
Requires-Dist: matplotlib
Requires-Dist: seaborn
Requires-Dist: dm-haiku
Provides-Extra: dev
Requires-Dist: torch >=1.7.0 ; extra == 'dev'
Requires-Dist: causalgraphicalmodels ; extra == 'dev'
Requires-Dist: pre-commit ; extra == 'dev'
Requires-Dist: datasets ; extra == 'dev'
Requires-Dist: nbdev >=v2.3.28 ; extra == 'dev'
Requires-Dist: jupyter ; extra == 'dev'
